MANIFEST.in
README.rst
setup.py
greek_stemmer/__init__.py
greek_stemmer/stemmer.yml
greek_stemmer.egg-info/PKG-INFO
greek_stemmer.egg-info/SOURCES.txt
greek_stemmer.egg-info/dependency_links.txt
greek_stemmer.egg-info/not-zip-safe
greek_stemmer.egg-info/requires.txt
greek_stemmer.egg-info/top_level.txt