Metadata-Version: 1.1
Name: greek-stemmer
Version: 0.1.1
Summary: Python Greek stemmer.
Home-page: https://github.com/alup/python_greek_stemmer
Author: Andreas Loupasakis
Author-email: alup@skroutz.gr
License: MIT
Keywords: stemmer greek nlp
Platform: UNKNOWN
Classifier: Development Status :: 4 - Beta
Classifier: Intended Audience :: Developers
Classifier: License :: OSI Approved :: MIT License
Classifier: Programming Language :: Python
Classifier: Programming Language :: Python :: 2.7
Classifier: Programming Language :: Python :: 3
Classifier: Programming Language :: Python :: 3.5
